[
  {
    "ContainingType": "Backend.Controllers.UsersController",
    "Method": "SignUp",
    "RelativePath": "api/Users/signup",
    "HttpMethod": "POST",
    "IsController": true,
    "Order": 0,
    "Parameters": [
      {
        "Name": "dTOUserSignUp",
        "Type": "BL.DTO.DTOUserSignUp",
        "IsRequired": true
      }
    ],
    "ReturnTypes": [
      {
        "Type": "System.Void",
        "MediaTypes": [],
        "StatusCode": 200
      },
      {
        "Type": "Backend.Responses.ErrorResponse",
        "MediaTypes": [
          "text/plain",
          "application/json",
          "text/json"
        ],
        "StatusCode": 400
      }
    ]
  },
  {
    "ContainingType": "Backend.MinimalAPIs.OTPEndpoints\u002B\u003C\u003Ec",
    "Method": "\u003CMapOTPEndpoints\u003Eb__1_0",
    "RelativePath": "otp/send-phone",
    "HttpMethod": "POST",
    "IsController": false,
    "Order": 0,
    "Parameters": [
      {
        "Name": "dTOOTPSendPhone",
        "Type": "BL.DTO.DTOOTPSendPhone",
        "IsRequired": true
      }
    ],
    "ReturnTypes": [
      {
        "Type": "System.Void",
        "MediaTypes": [],
        "StatusCode": 200
      }
    ]
  },
  {
    "ContainingType": "Backend.MinimalAPIs.OTPEndpoints\u002B\u003C\u003Ec",
    "Method": "\u003CMapOTPEndpoints\u003Eb__1_1",
    "RelativePath": "otp/validate-phone",
    "HttpMethod": "POST",
    "IsController": false,
    "Order": 0,
    "Parameters": [
      {
        "Name": "dTOOTPValidatePhone",
        "Type": "BL.DTO.DTOOTPValidatePhone",
        "IsRequired": true
      }
    ],
    "ReturnTypes": [
      {
        "Type": "System.String",
        "MediaTypes": [
          "text/plain"
        ],
        "StatusCode": 200
      }
    ]
  }
]